cypack/__init__.py
cypack/build.py
cypack/init.py
cypack/py.typed
cypack-0.0.2.dev7.dist-info/AUTHORS
cypack-0.0.2.dev7.dist-info/METADATA
cypack-0.0.2.dev7.dist-info/WHEEL
cypack-0.0.2.dev7.dist-info/entry_points.txt
cypack-0.0.2.dev7.dist-info/pbr.json
cypack-0.0.2.dev7.dist-info/top_level.txt
cypack-0.0.2.dev7.dist-info/RECORD
